mst/privsys/__init__.py
mst/privsys/privsys.py
mst_privsys-1.2.0.dist-info/METADATA
mst_privsys-1.2.0.dist-info/WHEEL
mst_privsys-1.2.0.dist-info/top_level.txt
mst_privsys-1.2.0.dist-info/RECORD
