Metadata-Version: 2.1
Name: mst-privsys
Version: 1.2.0
Summary: An interface to privsys for privilege lookup.
Author-email: Missouri University of Science and Technology - Information Technology <it-ai@mst.edu>
Requires-Python: >=3.8
Requires-Dist: mst-core
Requires-Dist: mst-simplerpc
Provides-Extra: tests
Requires-Dist: pytest ; extra == 'tests'
Requires-Dist: pytest-cov ; extra == 'tests'
Requires-Dist: tox ; extra == 'tests'
